[
    {
        "id": "001",
        "datetime": "08.03.2025 09:10:02",
        "status": "Neověřeno",
        "total_price": "545 Kč",
        "delivery": "Neznámý",
        "customer": {
            "name": "Martina Tomankova",
            "address": "Klášterní 415, Červenka",
            "phone": "737807847"
        },
        "products": [
            {
                "name": "25 Di Pietro (50 cm)",
                "price": "301 Kč + 15 Kč obal"
            },
            {
                "name": "BEZLEPKOVÁ 8 Hawaii (32 cm)",
                "price": "219 Kč + 10 Kč obal"
            }
        ]
    },
    {
        "id": "002",
        "datetime": "08.03.2025 09:54:02",
        "status": "Neověřeno",
        "total_price": "482 Kč",
        "delivery": "Neznámý",
        "customer": {
            "name": "Lubomír Satorova",
            "address": "Pňovice 286, Pňovice",
            "phone": "774518737"
        },
        "products": [
            {
                "name": "43 Quattro Formaggi Maestro (40 cm)",
                "price": "239 Kč + 12 Kč obal"
            },
            {
                "name": "6 Prosciuto (40 cm)",
                "price": "219 Kč + 12 Kč obal"
            }
        ]
    },
    {
        "id": "003",
        "datetime": "08.03.2025 10:20:15",
        "status": "Neověřeno",
        "total_price": "610 Kč",
        "delivery": "Neznámý",
        "customer": {
            "name": "Petr Novák",
            "address": "Masarykova 123, Brno",
            "phone": "731456789"
        },
        "products": [
            {
                "name": "10 Salami Special (50 cm)",
                "price": "289 Kč + 15 Kč obal"
            },
            {
                "name": "25 Di Pietro (40 cm)",
                "price": "289 Kč + 15 Kč obal"
            }
        ]
    },
    {
        "id": "004",
        "datetime": "08.03.2025 11:05:45",
        "status": "Neověřeno",
        "total_price": "495 Kč",
        "delivery": "Neznámý",
        "customer": {
            "name": "Jana Dvořáková",
            "address": "Jiráskova 45, Olomouc",
            "phone": "602345678"
        },
        "products": [
            {
                "name": "6 Prosciuto (40 cm)",
                "price": "219 Kč + 12 Kč obal"
            },
            {
                "name": "43 Quattro Formaggi Maestro (50 cm)",
                "price": "250 Kč + 14 Kč obal"
            }
        ]
    },
    {
        "id": "005",
        "datetime": "08.03.2025 12:30:32",
        "status": "Neověřeno",
        "total_price": "720 Kč",
        "delivery": "Neznámý",
        "customer": {
            "name": "Lukáš Marek",
            "address": "Husova 23, Plzeň",
            "phone": "777123456"
        },
        "products": [
            {
                "name": "25 Di Pietro (50 cm)",
                "price": "301 Kč + 15 Kč obal"
            },
            {
                "name": "BEZLEPKOVÁ 8 Hawaii (40 cm)",
                "price": "249 Kč + 12 Kč obal"
            }
        ]
    }
]